[
    {
        "key": "shift+cmd+\\",
        "command": "workbench.action.splitEditor"
    },
    {
        "key": "cmd+\\",
        "command": "-workbench.action.splitEditor"
    },
    {
        "key": "ctrl+alt+cmd+n",
        "command": "workbench.action.files.newUntitledFile"
    },
    {
        "key": "cmd+n",
        "command": "-workbench.action.files.newUntitledFile"
    },
    {
        "key": "shift+cmd+n",
        "command": "welcome.showNewFileEntries"
    },
    {
        "key": "ctrl+alt+cmd+n",
        "command": "-welcome.showNewFileEntries"
    },
    {
        "key": "cmd+n",
        "command": "explorer.newFile"
    },
    {
        "key": "cmd+enter",
        "command": "python.execInTerminal"
    },
    {
        "key": "shift+enter",
        "command": "workbench.action.terminal.sendSequence",
        "args": {
            "text": "\\\r\n"
        },
        "when": "terminalFocus"
    }
]